{
  "name": "Customer",
  "fields": [
    {
      "fieldName": "customerId",
      "fieldType": "Integer"
    },
    {
      "fieldName": "companyId",
      "fieldType": "Integer"
    },
    {
      "fieldName": "contactEmail",
      "fieldType": "String"
    },
    {
      "fieldName": "contactCreatedAt",
      "fieldType": "LocalDate"
    },
    {
      "fieldName": "contactModifiedAt",
      "fieldType": "LocalDate"
    }
  ],
  "relationships": [
    {
      "relationshipType": "many-to-one",
      "otherEntityName": "company",
      "otherEntityRelationshipName": "customer",
      "relationshipName": "company",
      "otherEntityField": "id"
    }
  ],
  "changelogDate": "20210311154652",
  "entityTableName": "customer",
  "dto": "no",
  "pagination": "no",
  "service": "no",
  "jpaMetamodelFiltering": false,
  "fluentMethods": true,
  "readOnly": false,
  "embedded": false,
  "clientRootFolder": "",
  "applications": ["dashboard"]
}
